__init__.py
binpan.py
handlers/__init__.py
handlers/exceptions.py
handlers/files_filters.py
handlers/logs.py
handlers/market.py
handlers/plotting.py
handlers/quest.py
handlers/starters.py
handlers/time_helper.py
handlers/wallet.py
binpan-0.0.3.dist-info/LICENSE
binpan-0.0.3.dist-info/METADATA
binpan-0.0.3.dist-info/WHEEL
binpan-0.0.3.dist-info/top_level.txt
binpan-0.0.3.dist-info/RECORD
