Metadata-Version: 2.1
Name: binpan
Version: 0.0.3
Summary: Binance API wrapper with backtesting tools.
Home-page: https://github.com/nand0san/binpan_studio
Author: Fernando Alfonso
Author-email: hancaidolosdos@hotmail.com
License: MIT
Classifier: License :: OSI Approved :: MIT License
Classifier: Programming Language :: Python :: 3
Classifier: Programming Language :: Python :: 3.9
License-File: LICENSE
Requires-Dist: requests (~=2.28.0)
Requires-Dist: pytz (~=2022.1)
Requires-Dist: py-cpuinfo (~=8.0.0)
Requires-Dist: numpy (==1.23.0)
Requires-Dist: pandas (~=1.4.2)
Requires-Dist: plotly (~=5.9.0)
Requires-Dist: tqdm (~=4.64.0)
Requires-Dist: pycryptodome (==3.15.0)
Requires-Dist: pandas-ta (==0.3.14b0)
